testpkg4_ftcao/__init__.py
testpkg4_ftcao/testpkg4_ftcao.py
testpkg4_ftcao-0.1.0.dist-info/LICENSE
testpkg4_ftcao-0.1.0.dist-info/METADATA
testpkg4_ftcao-0.1.0.dist-info/WHEEL
testpkg4_ftcao-0.1.0.dist-info/RECORD
